async_paho_mqtt_client.py
async_paho_mqtt_client-0.3.5.dist-info/METADATA
async_paho_mqtt_client-0.3.5.dist-info/WHEEL
async_paho_mqtt_client-0.3.5.dist-info/top_level.txt
async_paho_mqtt_client-0.3.5.dist-info/RECORD
