Metadata-Version: 2.2
Name: async-paho-mqtt-client
Version: 0.3.5
Home-page: https://github.com/mortbauer/async-paho-mqtt-client
Author: Martin Ortbauer
Author-email: martin@villagefarmer.net
License: MIT
Requires-Python: >=3.5
Requires-Dist: paho-mqtt
